README.rst
setup.py
brackets_cutter/__init__.py
brackets_cutter/core.py
brackets_cutter/tests.py
brackets_cutter.egg-info/PKG-INFO
brackets_cutter.egg-info/SOURCES.txt
brackets_cutter.egg-info/dependency_links.txt
brackets_cutter.egg-info/entry_points.txt
brackets_cutter.egg-info/top_level.txt